labbcat/AGQL.py
labbcat/LabbcatAdmin.py
labbcat/LabbcatEdit.py
labbcat/LabbcatView.py
labbcat/PraatScript.py
labbcat/Response.py
labbcat/ResponseException.py
labbcat/__init__.py
labbcat/version.py
nzilbb_labbcat-1.1.1.dist-info/licenses/LICENSE
nzilbb_labbcat-1.1.1.dist-info/METADATA
nzilbb_labbcat-1.1.1.dist-info/WHEEL
nzilbb_labbcat-1.1.1.dist-info/top_level.txt
nzilbb_labbcat-1.1.1.dist-info/RECORD
