Metadata-Version: 2.4
Name: nzilbb-labbcat
Version: 1.1.1
Summary: Client library for communicating with LaBB-CAT servers
Home-page: https://github.com/nzilbb/labbcat-py/
Author: Robert Fromont
Author-email: robert@fromont.net.nz
License: GPL-3.0-or-later
Classifier: License :: OSI Approved :: GNU General Public License v3 or later (GPLv3+)
Classifier: Programming Language :: Python :: 3
Classifier: Programming Language :: Python :: 3.7
License-File: LICENSE
Requires-Dist: requests
Dynamic: author
Dynamic: author-email
Dynamic: classifier
Dynamic: description
Dynamic: description-content-type
Dynamic: home-page
Dynamic: license
Dynamic: license-file
Dynamic: requires-dist
Dynamic: summary
